<?xml version="1.0" encoding="UTF-8"?>
<?xml-stylesheet href="CoreNLP-to-HTML.xsl" type="text/xsl"?>
<root>
  <document>
    <sentences>
      <sentence id="1">
        <tokens>
          <token id="1">
            <word>``</word>
            <CharacterOffsetBegin>0</CharacterOffsetBegin>
            <CharacterOffsetEnd>2</CharacterOffsetEnd>
            <POS>``</POS>
          </token>
          <token id="2">
            <word>There</word>
            <CharacterOffsetBegin>3</CharacterOffsetBegin>
            <CharacterOffsetEnd>8</CharacterOffsetEnd>
            <POS>RB</POS>
          </token>
          <token id="3">
            <word>I</word>
            <CharacterOffsetBegin>9</CharacterOffsetBegin>
            <CharacterOffsetEnd>10</CharacterOffsetEnd>
            <POS>PRP</POS>
          </token>
          <token id="4">
            <word>was</word>
            <CharacterOffsetBegin>11</CharacterOffsetBegin>
            <CharacterOffsetEnd>14</CharacterOffsetEnd>
            <POS>VBD</POS>
          </token>
          <token id="5">
            <word>in</word>
            <CharacterOffsetBegin>15</CharacterOffsetBegin>
            <CharacterOffsetEnd>17</CharacterOffsetEnd>
            <POS>IN</POS>
          </token>
          <token id="6">
            <word>our</word>
            <CharacterOffsetBegin>18</CharacterOffsetBegin>
            <CharacterOffsetEnd>21</CharacterOffsetEnd>
            <POS>PRP$</POS>
          </token>
          <token id="7">
            <word>``</word>
            <CharacterOffsetBegin>22</CharacterOffsetBegin>
            <CharacterOffsetEnd>24</CharacterOffsetEnd>
            <POS>``</POS>
          </token>
          <token id="8">
            <word>ouse</word>
            <CharacterOffsetBegin>25</CharacterOffsetBegin>
            <CharacterOffsetEnd>29</CharacterOffsetEnd>
            <POS>NN</POS>
          </token>
          <token id="9">
            <word>reading</word>
            <CharacterOffsetBegin>30</CharacterOffsetBegin>
            <CharacterOffsetEnd>37</CharacterOffsetEnd>
            <POS>VBG</POS>
          </token>
          <token id="10">
            <word>the</word>
            <CharacterOffsetBegin>38</CharacterOffsetBegin>
            <CharacterOffsetEnd>41</CharacterOffsetEnd>
            <POS>DT</POS>
          </token>
          <token id="11">
            <word>Labour</word>
            <CharacterOffsetBegin>42</CharacterOffsetBegin>
            <CharacterOffsetEnd>48</CharacterOffsetEnd>
            <POS>NNP</POS>
          </token>
          <token id="12">
            <word>manifesto</word>
            <CharacterOffsetBegin>49</CharacterOffsetBegin>
            <CharacterOffsetEnd>58</CharacterOffsetEnd>
            <POS>NN</POS>
          </token>
          <token id="13">
            <word>to</word>
            <CharacterOffsetBegin>59</CharacterOffsetBegin>
            <CharacterOffsetEnd>61</CharacterOffsetEnd>
            <POS>TO</POS>
          </token>
          <token id="14">
            <word>Our</word>
            <CharacterOffsetBegin>62</CharacterOffsetBegin>
            <CharacterOffsetEnd>65</CharacterOffsetEnd>
            <POS>NNP</POS>
          </token>
          <token id="15">
            <word>Jack</word>
            <CharacterOffsetBegin>66</CharacterOffsetBegin>
            <CharacterOffsetEnd>70</CharacterOffsetEnd>
            <POS>NNP</POS>
          </token>
          <token id="16">
            <word>--</word>
            <CharacterOffsetBegin>71</CharacterOffsetBegin>
            <CharacterOffsetEnd>74</CharacterOffsetEnd>
            <POS>:</POS>
          </token>
          <token id="17">
            <word>well</word>
            <CharacterOffsetBegin>75</CharacterOffsetBegin>
            <CharacterOffsetEnd>79</CharacterOffsetEnd>
            <POS>RB</POS>
          </token>
          <token id="18">
            <word>,</word>
            <CharacterOffsetBegin>80</CharacterOffsetBegin>
            <CharacterOffsetEnd>81</CharacterOffsetEnd>
            <POS>,</POS>
          </token>
          <token id="19">
            <word>he</word>
            <CharacterOffsetBegin>82</CharacterOffsetBegin>
            <CharacterOffsetEnd>84</CharacterOffsetEnd>
            <POS>PRP</POS>
          </token>
          <token id="20">
            <word>loves</word>
            <CharacterOffsetBegin>85</CharacterOffsetBegin>
            <CharacterOffsetEnd>90</CharacterOffsetEnd>
            <POS>VBZ</POS>
          </token>
          <token id="21">
            <word>fairy</word>
            <CharacterOffsetBegin>91</CharacterOffsetBegin>
            <CharacterOffsetEnd>96</CharacterOffsetEnd>
            <POS>NN</POS>
          </token>
          <token id="22">
            <word>stories</word>
            <CharacterOffsetBegin>97</CharacterOffsetBegin>
            <CharacterOffsetEnd>104</CharacterOffsetEnd>
            <POS>NNS</POS>
          </token>
          <token id="23">
            <word>...</word>
            <CharacterOffsetBegin>105</CharacterOffsetBegin>
            <CharacterOffsetEnd>108</CharacterOffsetEnd>
            <POS>:</POS>
          </token>
          <token id="24">
            <word>''</word>
            <CharacterOffsetBegin>109</CharacterOffsetBegin>
            <CharacterOffsetEnd>111</CharacterOffsetEnd>
            <POS>''</POS>
          </token>
          <token id="25">
            <word>she</word>
            <CharacterOffsetBegin>112</CharacterOffsetBegin>
            <CharacterOffsetEnd>115</CharacterOffsetEnd>
            <POS>PRP</POS>
          </token>
          <token id="26">
            <word>began</word>
            <CharacterOffsetBegin>116</CharacterOffsetBegin>
            <CharacterOffsetEnd>121</CharacterOffsetEnd>
            <POS>VBD</POS>
          </token>
          <token id="27">
            <word>,</word>
            <CharacterOffsetBegin>122</CharacterOffsetBegin>
            <CharacterOffsetEnd>123</CharacterOffsetEnd>
            <POS>,</POS>
          </token>
          <token id="28">
            <word>her</word>
            <CharacterOffsetBegin>124</CharacterOffsetBegin>
            <CharacterOffsetEnd>127</CharacterOffsetEnd>
            <POS>PRP$</POS>
          </token>
          <token id="29">
            <word>audience</word>
            <CharacterOffsetBegin>128</CharacterOffsetBegin>
            <CharacterOffsetEnd>136</CharacterOffsetEnd>
            <POS>NN</POS>
          </token>
          <token id="30">
            <word>lapping</word>
            <CharacterOffsetBegin>137</CharacterOffsetBegin>
            <CharacterOffsetEnd>144</CharacterOffsetEnd>
            <POS>VBG</POS>
          </token>
          <token id="31">
            <word>it</word>
            <CharacterOffsetBegin>145</CharacterOffsetBegin>
            <CharacterOffsetEnd>147</CharacterOffsetEnd>
            <POS>PRP</POS>
          </token>
          <token id="32">
            <word>up</word>
            <CharacterOffsetBegin>148</CharacterOffsetBegin>
            <CharacterOffsetEnd>150</CharacterOffsetEnd>
            <POS>RP</POS>
          </token>
          <token id="33">
            <word>.</word>
            <CharacterOffsetBegin>150</CharacterOffsetBegin>
            <CharacterOffsetEnd>151</CharacterOffsetEnd>
            <POS>.</POS>
          </token>
        </tokens>
        <parse>(ROOT (S (`` ``) (S (ADVP (RB There)) (NP (PRP I)) (VP (VBD was) (PP (IN in) (NP (NP (PRP$ our) (`` ``) (NN ouse)) (VP (VBG reading) (NP (DT the) (NNP Labour) (NN manifesto)) (PP (TO to) (NP (NNP Our) (NNP Jack))) (: --) (FRAG (ADVP (RB well)) (, ,) (S (NP (PRP he)) (VP (VBZ loves) (NP (NN fairy) (NNS stories)))) (: ...))))))) ('' '') (NP (PRP she)) (VP (VBD began) (, ,) (S (NP (PRP$ her) (NN audience)) (VP (VBG lapping) (NP (PRP it)) (PRT (RP up))))) (. .))) </parse>
        <dependencies type="basic-dependencies">
          <dep type="root">
            <governor idx="0">ROOT</governor>
            <dependent idx="26">began</dependent>
          </dep>
          <dep type="advmod">
            <governor idx="4">was</governor>
            <dependent idx="2">There</dependent>
          </dep>
          <dep type="nsubj">
            <governor idx="4">was</governor>
            <dependent idx="3">I</dependent>
          </dep>
          <dep type="ccomp">
            <governor idx="26">began</governor>
            <dependent idx="4">was</dependent>
          </dep>
          <dep type="prep">
            <governor idx="4">was</governor>
            <dependent idx="5">in</dependent>
          </dep>
          <dep type="poss">
            <governor idx="8">ouse</governor>
            <dependent idx="6">our</dependent>
          </dep>
          <dep type="pobj">
            <governor idx="5">in</governor>
            <dependent idx="8">ouse</dependent>
          </dep>
          <dep type="vmod">
            <governor idx="8">ouse</governor>
            <dependent idx="9">reading</dependent>
          </dep>
          <dep type="det">
            <governor idx="12">manifesto</governor>
            <dependent idx="10">the</dependent>
          </dep>
          <dep type="nn">
            <governor idx="12">manifesto</governor>
            <dependent idx="11">Labour</dependent>
          </dep>
          <dep type="dobj">
            <governor idx="9">reading</governor>
            <dependent idx="12">manifesto</dependent>
          </dep>
          <dep type="prep">
            <governor idx="9">reading</governor>
            <dependent idx="13">to</dependent>
          </dep>
          <dep type="nn">
            <governor idx="15">Jack</governor>
            <dependent idx="14">Our</dependent>
          </dep>
          <dep type="pobj">
            <governor idx="13">to</governor>
            <dependent idx="15">Jack</dependent>
          </dep>
          <dep type="dep">
            <governor idx="9">reading</governor>
            <dependent idx="17">well</dependent>
          </dep>
          <dep type="nsubj">
            <governor idx="20">loves</governor>
            <dependent idx="19">he</dependent>
          </dep>
          <dep type="dep">
            <governor idx="17">well</governor>
            <dependent idx="20">loves</dependent>
          </dep>
          <dep type="nn">
            <governor idx="22">stories</governor>
            <dependent idx="21">fairy</dependent>
          </dep>
          <dep type="dobj">
            <governor idx="20">loves</governor>
            <dependent idx="22">stories</dependent>
          </dep>
          <dep type="nsubj">
            <governor idx="26">began</governor>
            <dependent idx="25">she</dependent>
          </dep>
          <dep type="poss">
            <governor idx="29">audience</governor>
            <dependent idx="28">her</dependent>
          </dep>
          <dep type="nsubj">
            <governor idx="30">lapping</governor>
            <dependent idx="29">audience</dependent>
          </dep>
          <dep type="dep">
            <governor idx="26">began</governor>
            <dependent idx="30">lapping</dependent>
          </dep>
          <dep type="dobj">
            <governor idx="30">lapping</governor>
            <dependent idx="31">it</dependent>
          </dep>
          <dep type="prt">
            <governor idx="30">lapping</governor>
            <dependent idx="32">up</dependent>
          </dep>
        </dependencies>
        <dependencies type="collapsed-dependencies">
          <dep type="root">
            <governor idx="0">ROOT</governor>
            <dependent idx="26">began</dependent>
          </dep>
          <dep type="advmod">
            <governor idx="4">was</governor>
            <dependent idx="2">There</dependent>
          </dep>
          <dep type="nsubj">
            <governor idx="4">was</governor>
            <dependent idx="3">I</dependent>
          </dep>
          <dep type="ccomp">
            <governor idx="26">began</governor>
            <dependent idx="4">was</dependent>
          </dep>
          <dep type="poss">
            <governor idx="8">ouse</governor>
            <dependent idx="6">our</dependent>
          </dep>
          <dep type="prep_in">
            <governor idx="4">was</governor>
            <dependent idx="8">ouse</dependent>
          </dep>
          <dep type="vmod">
            <governor idx="8">ouse</governor>
            <dependent idx="9">reading</dependent>
          </dep>
          <dep type="det">
            <governor idx="12">manifesto</governor>
            <dependent idx="10">the</dependent>
          </dep>
          <dep type="nn">
            <governor idx="12">manifesto</governor>
            <dependent idx="11">Labour</dependent>
          </dep>
          <dep type="dobj">
            <governor idx="9">reading</governor>
            <dependent idx="12">manifesto</dependent>
          </dep>
          <dep type="nn">
            <governor idx="15">Jack</governor>
            <dependent idx="14">Our</dependent>
          </dep>
          <dep type="prep_to">
            <governor idx="9">reading</governor>
            <dependent idx="15">Jack</dependent>
          </dep>
          <dep type="dep">
            <governor idx="9">reading</governor>
            <dependent idx="17">well</dependent>
          </dep>
          <dep type="nsubj">
            <governor idx="20">loves</governor>
            <dependent idx="19">he</dependent>
          </dep>
          <dep type="dep">
            <governor idx="17">well</governor>
            <dependent idx="20">loves</dependent>
          </dep>
          <dep type="nn">
            <governor idx="22">stories</governor>
            <dependent idx="21">fairy</dependent>
          </dep>
          <dep type="dobj">
            <governor idx="20">loves</governor>
            <dependent idx="22">stories</dependent>
          </dep>
          <dep type="nsubj">
            <governor idx="26">began</governor>
            <dependent idx="25">she</dependent>
          </dep>
          <dep type="poss">
            <governor idx="29">audience</governor>
            <dependent idx="28">her</dependent>
          </dep>
          <dep type="nsubj">
            <governor idx="30">lapping</governor>
            <dependent idx="29">audience</dependent>
          </dep>
          <dep type="dep">
            <governor idx="26">began</governor>
            <dependent idx="30">lapping</dependent>
          </dep>
          <dep type="dobj">
            <governor idx="30">lapping</governor>
            <dependent idx="31">it</dependent>
          </dep>
          <dep type="prt">
            <governor idx="30">lapping</governor>
            <dependent idx="32">up</dependent>
          </dep>
        </dependencies>
        <dependencies type="collapsed-ccprocessed-dependencies">
          <dep type="root">
            <governor idx="0">ROOT</governor>
            <dependent idx="26">began</dependent>
          </dep>
          <dep type="advmod">
            <governor idx="4">was</governor>
            <dependent idx="2">There</dependent>
          </dep>
          <dep type="nsubj">
            <governor idx="4">was</governor>
            <dependent idx="3">I</dependent>
          </dep>
          <dep type="ccomp">
            <governor idx="26">began</governor>
            <dependent idx="4">was</dependent>
          </dep>
          <dep type="poss">
            <governor idx="8">ouse</governor>
            <dependent idx="6">our</dependent>
          </dep>
          <dep type="prep_in">
            <governor idx="4">was</governor>
            <dependent idx="8">ouse</dependent>
          </dep>
          <dep type="vmod">
            <governor idx="8">ouse</governor>
            <dependent idx="9">reading</dependent>
          </dep>
          <dep type="det">
            <governor idx="12">manifesto</governor>
            <dependent idx="10">the</dependent>
          </dep>
          <dep type="nn">
            <governor idx="12">manifesto</governor>
            <dependent idx="11">Labour</dependent>
          </dep>
          <dep type="dobj">
            <governor idx="9">reading</governor>
            <dependent idx="12">manifesto</dependent>
          </dep>
          <dep type="nn">
            <governor idx="15">Jack</governor>
            <dependent idx="14">Our</dependent>
          </dep>
          <dep type="prep_to">
            <governor idx="9">reading</governor>
            <dependent idx="15">Jack</dependent>
          </dep>
          <dep type="dep">
            <governor idx="9">reading</governor>
            <dependent idx="17">well</dependent>
          </dep>
          <dep type="nsubj">
            <governor idx="20">loves</governor>
            <dependent idx="19">he</dependent>
          </dep>
          <dep type="dep">
            <governor idx="17">well</governor>
            <dependent idx="20">loves</dependent>
          </dep>
          <dep type="nn">
            <governor idx="22">stories</governor>
            <dependent idx="21">fairy</dependent>
          </dep>
          <dep type="dobj">
            <governor idx="20">loves</governor>
            <dependent idx="22">stories</dependent>
          </dep>
          <dep type="nsubj">
            <governor idx="26">began</governor>
            <dependent idx="25">she</dependent>
          </dep>
          <dep type="poss">
            <governor idx="29">audience</governor>
            <dependent idx="28">her</dependent>
          </dep>
          <dep type="nsubj">
            <governor idx="30">lapping</governor>
            <dependent idx="29">audience</dependent>
          </dep>
          <dep type="dep">
            <governor idx="26">began</governor>
            <dependent idx="30">lapping</dependent>
          </dep>
          <dep type="dobj">
            <governor idx="30">lapping</governor>
            <dependent idx="31">it</dependent>
          </dep>
          <dep type="prt">
            <governor idx="30">lapping</governor>
            <dependent idx="32">up</dependent>
          </dep>
        </dependencies>
      </sentence>
      <sentence id="2">
        <tokens>
          <token id="1">
            <word>Accomplished</word>
            <CharacterOffsetBegin>152</CharacterOffsetBegin>
            <CharacterOffsetEnd>164</CharacterOffsetEnd>
            <POS>NNP</POS>
          </token>
          <token id="2">
            <word>compere</word>
            <CharacterOffsetBegin>165</CharacterOffsetBegin>
            <CharacterOffsetEnd>172</CharacterOffsetEnd>
            <POS>VBP</POS>
          </token>
          <token id="3">
            <word>that</word>
            <CharacterOffsetBegin>173</CharacterOffsetBegin>
            <CharacterOffsetEnd>177</CharacterOffsetEnd>
            <POS>IN</POS>
          </token>
          <token id="4">
            <word>she</word>
            <CharacterOffsetBegin>178</CharacterOffsetBegin>
            <CharacterOffsetEnd>181</CharacterOffsetEnd>
            <POS>PRP</POS>
          </token>
          <token id="5">
            <word>is</word>
            <CharacterOffsetBegin>182</CharacterOffsetBegin>
            <CharacterOffsetEnd>184</CharacterOffsetEnd>
            <POS>VBZ</POS>
          </token>
          <token id="6">
            <word>,</word>
            <CharacterOffsetBegin>185</CharacterOffsetBegin>
            <CharacterOffsetEnd>186</CharacterOffsetEnd>
            <POS>,</POS>
          </token>
          <token id="7">
            <word>she</word>
            <CharacterOffsetBegin>187</CharacterOffsetBegin>
            <CharacterOffsetEnd>190</CharacterOffsetEnd>
            <POS>PRP</POS>
          </token>
          <token id="8">
            <word>knew</word>
            <CharacterOffsetBegin>191</CharacterOffsetBegin>
            <CharacterOffsetEnd>195</CharacterOffsetEnd>
            <POS>VBD</POS>
          </token>
          <token id="9">
            <word>just</word>
            <CharacterOffsetBegin>196</CharacterOffsetBegin>
            <CharacterOffsetEnd>200</CharacterOffsetEnd>
            <POS>RB</POS>
          </token>
          <token id="10">
            <word>when</word>
            <CharacterOffsetBegin>201</CharacterOffsetBegin>
            <CharacterOffsetEnd>205</CharacterOffsetEnd>
            <POS>WRB</POS>
          </token>
          <token id="11">
            <word>to</word>
            <CharacterOffsetBegin>206</CharacterOffsetBegin>
            <CharacterOffsetEnd>208</CharacterOffsetEnd>
            <POS>TO</POS>
          </token>
          <token id="12">
            <word>stick</word>
            <CharacterOffsetBegin>209</CharacterOffsetBegin>
            <CharacterOffsetEnd>214</CharacterOffsetEnd>
            <POS>VB</POS>
          </token>
          <token id="13">
            <word>in</word>
            <CharacterOffsetBegin>215</CharacterOffsetBegin>
            <CharacterOffsetEnd>217</CharacterOffsetEnd>
            <POS>IN</POS>
          </token>
          <token id="14">
            <word>the</word>
            <CharacterOffsetBegin>218</CharacterOffsetBegin>
            <CharacterOffsetEnd>221</CharacterOffsetEnd>
            <POS>DT</POS>
          </token>
          <token id="15">
            <word>``</word>
            <CharacterOffsetBegin>222</CharacterOffsetBegin>
            <CharacterOffsetEnd>224</CharacterOffsetEnd>
            <POS>``</POS>
          </token>
          <token id="16">
            <word>but</word>
            <CharacterOffsetBegin>225</CharacterOffsetBegin>
            <CharacterOffsetEnd>228</CharacterOffsetEnd>
            <POS>CC</POS>
          </token>
          <token id="17">
            <word>seriously</word>
            <CharacterOffsetBegin>229</CharacterOffsetBegin>
            <CharacterOffsetEnd>238</CharacterOffsetEnd>
            <POS>RB</POS>
          </token>
          <token id="18">
            <word>,</word>
            <CharacterOffsetBegin>239</CharacterOffsetBegin>
            <CharacterOffsetEnd>240</CharacterOffsetEnd>
            <POS>,</POS>
          </token>
          <token id="19">
            <word>folks</word>
            <CharacterOffsetBegin>241</CharacterOffsetBegin>
            <CharacterOffsetEnd>246</CharacterOffsetEnd>
            <POS>NNS</POS>
          </token>
          <token id="20">
            <word>''</word>
            <CharacterOffsetBegin>247</CharacterOffsetBegin>
            <CharacterOffsetEnd>249</CharacterOffsetEnd>
            <POS>''</POS>
          </token>
          <token id="21">
            <word>bit</word>
            <CharacterOffsetBegin>250</CharacterOffsetBegin>
            <CharacterOffsetEnd>253</CharacterOffsetEnd>
            <POS>VBD</POS>
          </token>
          <token id="22">
            <word>.</word>
            <CharacterOffsetBegin>254</CharacterOffsetBegin>
            <CharacterOffsetEnd>255</CharacterOffsetEnd>
            <POS>.</POS>
          </token>
        </tokens>
        <parse>(ROOT (S (S (NP (NNP Accomplished)) (VP (VBP compere) (SBAR (IN that) (S (NP (PRP she)) (VP (VBZ is)))))) (PRN (, ,) (S (NP (PRP she)) (VP (VBD knew) (SBAR (RB just) (WHADVP (WRB when)) (S (VP (TO to) (VP (VB stick) (PP (IN in) (NP (DT the)))))))))) (`` ``) (CC but) (S (ADVP (RB seriously)) (, ,) (NP (NNS folks)) ('' '') (VP (VBD bit))) (. .))) </parse>
        <dependencies type="basic-dependencies">
          <dep type="root">
            <governor idx="0">ROOT</governor>
            <dependent idx="2">compere</dependent>
          </dep>
          <dep type="nsubj">
            <governor idx="2">compere</governor>
            <dependent idx="1">Accomplished</dependent>
          </dep>
          <dep type="mark">
            <governor idx="5">is</governor>
            <dependent idx="3">that</dependent>
          </dep>
          <dep type="nsubj">
            <governor idx="5">is</governor>
            <dependent idx="4">she</dependent>
          </dep>
          <dep type="ccomp">
            <governor idx="2">compere</governor>
            <dependent idx="5">is</dependent>
          </dep>
          <dep type="nsubj">
            <governor idx="8">knew</governor>
            <dependent idx="7">she</dependent>
          </dep>
          <dep type="dep">
            <governor idx="2">compere</governor>
            <dependent idx="8">knew</dependent>
          </dep>
          <dep type="advmod">
            <governor idx="12">stick</governor>
            <dependent idx="9">just</dependent>
          </dep>
          <dep type="advmod">
            <governor idx="12">stick</governor>
            <dependent idx="10">when</dependent>
          </dep>
          <dep type="aux">
            <governor idx="12">stick</governor>
            <dependent idx="11">to</dependent>
          </dep>
          <dep type="xcomp">
            <governor idx="8">knew</governor>
            <dependent idx="12">stick</dependent>
          </dep>
          <dep type="prep">
            <governor idx="12">stick</governor>
            <dependent idx="13">in</dependent>
          </dep>
          <dep type="pobj">
            <governor idx="13">in</governor>
            <dependent idx="14">the</dependent>
          </dep>
          <dep type="cc">
            <governor idx="2">compere</governor>
            <dependent idx="16">but</dependent>
          </dep>
          <dep type="advmod">
            <governor idx="21">bit</governor>
            <dependent idx="17">seriously</dependent>
          </dep>
          <dep type="nsubj">
            <governor idx="21">bit</governor>
            <dependent idx="19">folks</dependent>
          </dep>
          <dep type="conj">
            <governor idx="2">compere</governor>
            <dependent idx="21">bit</dependent>
          </dep>
        </dependencies>
        <dependencies type="collapsed-dependencies">
          <dep type="root">
            <governor idx="0">ROOT</governor>
            <dependent idx="2">compere</dependent>
          </dep>
          <dep type="nsubj">
            <governor idx="2">compere</governor>
            <dependent idx="1">Accomplished</dependent>
          </dep>
          <dep type="mark">
            <governor idx="5">is</governor>
            <dependent idx="3">that</dependent>
          </dep>
          <dep type="nsubj">
            <governor idx="5">is</governor>
            <dependent idx="4">she</dependent>
          </dep>
          <dep type="ccomp">
            <governor idx="2">compere</governor>
            <dependent idx="5">is</dependent>
          </dep>
          <dep type="nsubj">
            <governor idx="8">knew</governor>
            <dependent idx="7">she</dependent>
          </dep>
          <dep type="dep">
            <governor idx="2">compere</governor>
            <dependent idx="8">knew</dependent>
          </dep>
          <dep type="advmod">
            <governor idx="12">stick</governor>
            <dependent idx="9">just</dependent>
          </dep>
          <dep type="advmod">
            <governor idx="12">stick</governor>
            <dependent idx="10">when</dependent>
          </dep>
          <dep type="aux">
            <governor idx="12">stick</governor>
            <dependent idx="11">to</dependent>
          </dep>
          <dep type="xcomp">
            <governor idx="8">knew</governor>
            <dependent idx="12">stick</dependent>
          </dep>
          <dep type="prep_in">
            <governor idx="12">stick</governor>
            <dependent idx="14">the</dependent>
          </dep>
          <dep type="advmod">
            <governor idx="21">bit</governor>
            <dependent idx="17">seriously</dependent>
          </dep>
          <dep type="nsubj">
            <governor idx="21">bit</governor>
            <dependent idx="19">folks</dependent>
          </dep>
          <dep type="conj_but">
            <governor idx="2">compere</governor>
            <dependent idx="21">bit</dependent>
          </dep>
        </dependencies>
        <dependencies type="collapsed-ccprocessed-dependencies">
          <dep type="root">
            <governor idx="0">ROOT</governor>
            <dependent idx="2">compere</dependent>
          </dep>
          <dep type="nsubj">
            <governor idx="2">compere</governor>
            <dependent idx="1">Accomplished</dependent>
          </dep>
          <dep type="mark">
            <governor idx="5">is</governor>
            <dependent idx="3">that</dependent>
          </dep>
          <dep type="nsubj">
            <governor idx="5">is</governor>
            <dependent idx="4">she</dependent>
          </dep>
          <dep type="ccomp">
            <governor idx="2">compere</governor>
            <dependent idx="5">is</dependent>
          </dep>
          <dep type="nsubj">
            <governor idx="8">knew</governor>
            <dependent idx="7">she</dependent>
          </dep>
          <dep type="dep">
            <governor idx="2">compere</governor>
            <dependent idx="8">knew</dependent>
          </dep>
          <dep type="advmod">
            <governor idx="12">stick</governor>
            <dependent idx="9">just</dependent>
          </dep>
          <dep type="advmod">
            <governor idx="12">stick</governor>
            <dependent idx="10">when</dependent>
          </dep>
          <dep type="aux">
            <governor idx="12">stick</governor>
            <dependent idx="11">to</dependent>
          </dep>
          <dep type="xcomp">
            <governor idx="8">knew</governor>
            <dependent idx="12">stick</dependent>
          </dep>
          <dep type="prep_in">
            <governor idx="12">stick</governor>
            <dependent idx="14">the</dependent>
          </dep>
          <dep type="advmod">
            <governor idx="21">bit</governor>
            <dependent idx="17">seriously</dependent>
          </dep>
          <dep type="nsubj">
            <governor idx="21">bit</governor>
            <dependent idx="19">folks</dependent>
          </dep>
          <dep type="conj_but">
            <governor idx="2">compere</governor>
            <dependent idx="21">bit</dependent>
          </dep>
        </dependencies>
      </sentence>
    </sentences>
  </document>
</root>
