<?xml version="1.0" encoding="UTF-8"?>
<?xml-stylesheet href="CoreNLP-to-HTML.xsl" type="text/xsl"?>
<root>
  <document>
    <sentences>
      <sentence id="1">
        <tokens>
          <token id="1">
            <word>But</word>
            <CharacterOffsetBegin>0</CharacterOffsetBegin>
            <CharacterOffsetEnd>3</CharacterOffsetEnd>
            <POS>CC</POS>
          </token>
          <token id="2">
            <word>both</word>
            <CharacterOffsetBegin>4</CharacterOffsetBegin>
            <CharacterOffsetEnd>8</CharacterOffsetEnd>
            <POS>DT</POS>
          </token>
          <token id="3">
            <word>were</word>
            <CharacterOffsetBegin>9</CharacterOffsetBegin>
            <CharacterOffsetEnd>13</CharacterOffsetEnd>
            <POS>VBD</POS>
          </token>
          <token id="4">
            <word>killed</word>
            <CharacterOffsetBegin>14</CharacterOffsetBegin>
            <CharacterOffsetEnd>20</CharacterOffsetEnd>
            <POS>VBN</POS>
          </token>
          <token id="5">
            <word>--</word>
            <CharacterOffsetBegin>21</CharacterOffsetBegin>
            <CharacterOffsetEnd>24</CharacterOffsetEnd>
            <POS>:</POS>
          </token>
          <token id="6">
            <word>Abu</word>
            <CharacterOffsetBegin>25</CharacterOffsetBegin>
            <CharacterOffsetEnd>28</CharacterOffsetEnd>
            <POS>NNP</POS>
          </token>
          <token id="7">
            <word>Jihad</word>
            <CharacterOffsetBegin>29</CharacterOffsetBegin>
            <CharacterOffsetEnd>34</CharacterOffsetEnd>
            <POS>NNP</POS>
          </token>
          <token id="8">
            <word>by</word>
            <CharacterOffsetBegin>35</CharacterOffsetBegin>
            <CharacterOffsetEnd>37</CharacterOffsetEnd>
            <POS>IN</POS>
          </token>
          <token id="9">
            <word>an</word>
            <CharacterOffsetBegin>38</CharacterOffsetBegin>
            <CharacterOffsetEnd>40</CharacterOffsetEnd>
            <POS>DT</POS>
          </token>
          <token id="10">
            <word>Israeli</word>
            <CharacterOffsetBegin>41</CharacterOffsetBegin>
            <CharacterOffsetEnd>48</CharacterOffsetEnd>
            <POS>JJ</POS>
          </token>
          <token id="11">
            <word>hit</word>
            <CharacterOffsetBegin>49</CharacterOffsetBegin>
            <CharacterOffsetEnd>52</CharacterOffsetEnd>
            <POS>VBN</POS>
          </token>
          <token id="12">
            <word>squad</word>
            <CharacterOffsetBegin>53</CharacterOffsetBegin>
            <CharacterOffsetEnd>58</CharacterOffsetEnd>
            <POS>NN</POS>
          </token>
          <token id="13">
            <word>in</word>
            <CharacterOffsetBegin>59</CharacterOffsetBegin>
            <CharacterOffsetEnd>61</CharacterOffsetEnd>
            <POS>IN</POS>
          </token>
          <token id="14">
            <word>1988</word>
            <CharacterOffsetBegin>62</CharacterOffsetBegin>
            <CharacterOffsetEnd>66</CharacterOffsetEnd>
            <POS>CD</POS>
          </token>
          <token id="15">
            <word>,</word>
            <CharacterOffsetBegin>67</CharacterOffsetBegin>
            <CharacterOffsetEnd>68</CharacterOffsetEnd>
            <POS>,</POS>
          </token>
          <token id="16">
            <word>Abu</word>
            <CharacterOffsetBegin>69</CharacterOffsetBegin>
            <CharacterOffsetEnd>72</CharacterOffsetEnd>
            <POS>NNP</POS>
          </token>
          <token id="17">
            <word>Iyad</word>
            <CharacterOffsetBegin>73</CharacterOffsetBegin>
            <CharacterOffsetEnd>77</CharacterOffsetEnd>
            <POS>NNP</POS>
          </token>
          <token id="18">
            <word>by</word>
            <CharacterOffsetBegin>78</CharacterOffsetBegin>
            <CharacterOffsetEnd>80</CharacterOffsetEnd>
            <POS>IN</POS>
          </token>
          <token id="19">
            <word>a</word>
            <CharacterOffsetBegin>81</CharacterOffsetBegin>
            <CharacterOffsetEnd>82</CharacterOffsetEnd>
            <POS>DT</POS>
          </token>
          <token id="20">
            <word>supporter</word>
            <CharacterOffsetBegin>83</CharacterOffsetBegin>
            <CharacterOffsetEnd>92</CharacterOffsetEnd>
            <POS>NN</POS>
          </token>
          <token id="21">
            <word>of</word>
            <CharacterOffsetBegin>93</CharacterOffsetBegin>
            <CharacterOffsetEnd>95</CharacterOffsetEnd>
            <POS>IN</POS>
          </token>
          <token id="22">
            <word>the</word>
            <CharacterOffsetBegin>96</CharacterOffsetBegin>
            <CharacterOffsetEnd>99</CharacterOffsetEnd>
            <POS>DT</POS>
          </token>
          <token id="23">
            <word>breakaway</word>
            <CharacterOffsetBegin>100</CharacterOffsetBegin>
            <CharacterOffsetEnd>109</CharacterOffsetEnd>
            <POS>JJ</POS>
          </token>
          <token id="24">
            <word>Abu</word>
            <CharacterOffsetBegin>110</CharacterOffsetBegin>
            <CharacterOffsetEnd>113</CharacterOffsetEnd>
            <POS>NNP</POS>
          </token>
          <token id="25">
            <word>Nidal</word>
            <CharacterOffsetBegin>114</CharacterOffsetBegin>
            <CharacterOffsetEnd>119</CharacterOffsetEnd>
            <POS>NNP</POS>
          </token>
          <token id="26">
            <word>faction</word>
            <CharacterOffsetBegin>120</CharacterOffsetBegin>
            <CharacterOffsetEnd>127</CharacterOffsetEnd>
            <POS>NN</POS>
          </token>
          <token id="27">
            <word>three</word>
            <CharacterOffsetBegin>128</CharacterOffsetBegin>
            <CharacterOffsetEnd>133</CharacterOffsetEnd>
            <POS>CD</POS>
          </token>
          <token id="28">
            <word>years</word>
            <CharacterOffsetBegin>134</CharacterOffsetBegin>
            <CharacterOffsetEnd>139</CharacterOffsetEnd>
            <POS>NNS</POS>
          </token>
          <token id="29">
            <word>later</word>
            <CharacterOffsetBegin>140</CharacterOffsetBegin>
            <CharacterOffsetEnd>145</CharacterOffsetEnd>
            <POS>RB</POS>
          </token>
          <token id="30">
            <word>.</word>
            <CharacterOffsetBegin>146</CharacterOffsetBegin>
            <CharacterOffsetEnd>147</CharacterOffsetEnd>
            <POS>.</POS>
          </token>
        </tokens>
        <parse>(ROOT (S (CC But) (NP (DT both)) (VP (VBD were) (VP (VBN killed) (PRN (: --) (NP (NP (NNP Abu) (NNP Jihad)) (PP (IN by) (NP (NP (DT an) (JJ Israeli) (VBN hit) (NN squad)) (PP (IN in) (NP (NP (CD 1988)) (, ,) (NP (NNP Abu) (NNP Iyad)))))))) (PP (IN by) (NP (NP (DT a) (NN supporter)) (PP (IN of) (NP (DT the) (JJ breakaway) (NNP Abu) (NNP Nidal) (NN faction))))) (NP-TMP (CD three) (NNS years) (RB later)))) (. .))) </parse>
        <dependencies type="basic-dependencies">
          <dep type="root">
            <governor idx="0">ROOT</governor>
            <dependent idx="4">killed</dependent>
          </dep>
          <dep type="cc">
            <governor idx="4">killed</governor>
            <dependent idx="1">But</dependent>
          </dep>
          <dep type="nsubjpass">
            <governor idx="4">killed</governor>
            <dependent idx="2">both</dependent>
          </dep>
          <dep type="auxpass">
            <governor idx="4">killed</governor>
            <dependent idx="3">were</dependent>
          </dep>
          <dep type="nn">
            <governor idx="7">Jihad</governor>
            <dependent idx="6">Abu</dependent>
          </dep>
          <dep type="dep">
            <governor idx="4">killed</governor>
            <dependent idx="7">Jihad</dependent>
          </dep>
          <dep type="prep">
            <governor idx="7">Jihad</governor>
            <dependent idx="8">by</dependent>
          </dep>
          <dep type="det">
            <governor idx="12">squad</governor>
            <dependent idx="9">an</dependent>
          </dep>
          <dep type="amod">
            <governor idx="12">squad</governor>
            <dependent idx="10">Israeli</dependent>
          </dep>
          <dep type="amod">
            <governor idx="12">squad</governor>
            <dependent idx="11">hit</dependent>
          </dep>
          <dep type="pobj">
            <governor idx="8">by</governor>
            <dependent idx="12">squad</dependent>
          </dep>
          <dep type="prep">
            <governor idx="12">squad</governor>
            <dependent idx="13">in</dependent>
          </dep>
          <dep type="pobj">
            <governor idx="13">in</governor>
            <dependent idx="14">1988</dependent>
          </dep>
          <dep type="nn">
            <governor idx="17">Iyad</governor>
            <dependent idx="16">Abu</dependent>
          </dep>
          <dep type="appos">
            <governor idx="14">1988</governor>
            <dependent idx="17">Iyad</dependent>
          </dep>
          <dep type="prep">
            <governor idx="4">killed</governor>
            <dependent idx="18">by</dependent>
          </dep>
          <dep type="det">
            <governor idx="20">supporter</governor>
            <dependent idx="19">a</dependent>
          </dep>
          <dep type="pobj">
            <governor idx="18">by</governor>
            <dependent idx="20">supporter</dependent>
          </dep>
          <dep type="prep">
            <governor idx="20">supporter</governor>
            <dependent idx="21">of</dependent>
          </dep>
          <dep type="det">
            <governor idx="26">faction</governor>
            <dependent idx="22">the</dependent>
          </dep>
          <dep type="amod">
            <governor idx="26">faction</governor>
            <dependent idx="23">breakaway</dependent>
          </dep>
          <dep type="nn">
            <governor idx="26">faction</governor>
            <dependent idx="24">Abu</dependent>
          </dep>
          <dep type="nn">
            <governor idx="26">faction</governor>
            <dependent idx="25">Nidal</dependent>
          </dep>
          <dep type="pobj">
            <governor idx="21">of</governor>
            <dependent idx="26">faction</dependent>
          </dep>
          <dep type="num">
            <governor idx="28">years</governor>
            <dependent idx="27">three</dependent>
          </dep>
          <dep type="tmod">
            <governor idx="4">killed</governor>
            <dependent idx="28">years</dependent>
          </dep>
          <dep type="advmod">
            <governor idx="28">years</governor>
            <dependent idx="29">later</dependent>
          </dep>
        </dependencies>
        <dependencies type="collapsed-dependencies">
          <dep type="root">
            <governor idx="0">ROOT</governor>
            <dependent idx="4">killed</dependent>
          </dep>
          <dep type="cc">
            <governor idx="4">killed</governor>
            <dependent idx="1">But</dependent>
          </dep>
          <dep type="nsubjpass">
            <governor idx="4">killed</governor>
            <dependent idx="2">both</dependent>
          </dep>
          <dep type="auxpass">
            <governor idx="4">killed</governor>
            <dependent idx="3">were</dependent>
          </dep>
          <dep type="nn">
            <governor idx="7">Jihad</governor>
            <dependent idx="6">Abu</dependent>
          </dep>
          <dep type="dep">
            <governor idx="4">killed</governor>
            <dependent idx="7">Jihad</dependent>
          </dep>
          <dep type="det">
            <governor idx="12">squad</governor>
            <dependent idx="9">an</dependent>
          </dep>
          <dep type="amod">
            <governor idx="12">squad</governor>
            <dependent idx="10">Israeli</dependent>
          </dep>
          <dep type="amod">
            <governor idx="12">squad</governor>
            <dependent idx="11">hit</dependent>
          </dep>
          <dep type="prep_by">
            <governor idx="7">Jihad</governor>
            <dependent idx="12">squad</dependent>
          </dep>
          <dep type="prep_in">
            <governor idx="12">squad</governor>
            <dependent idx="14">1988</dependent>
          </dep>
          <dep type="nn">
            <governor idx="17">Iyad</governor>
            <dependent idx="16">Abu</dependent>
          </dep>
          <dep type="appos">
            <governor idx="14">1988</governor>
            <dependent idx="17">Iyad</dependent>
          </dep>
          <dep type="det">
            <governor idx="20">supporter</governor>
            <dependent idx="19">a</dependent>
          </dep>
          <dep type="agent">
            <governor idx="4">killed</governor>
            <dependent idx="20">supporter</dependent>
          </dep>
          <dep type="det">
            <governor idx="26">faction</governor>
            <dependent idx="22">the</dependent>
          </dep>
          <dep type="amod">
            <governor idx="26">faction</governor>
            <dependent idx="23">breakaway</dependent>
          </dep>
          <dep type="nn">
            <governor idx="26">faction</governor>
            <dependent idx="24">Abu</dependent>
          </dep>
          <dep type="nn">
            <governor idx="26">faction</governor>
            <dependent idx="25">Nidal</dependent>
          </dep>
          <dep type="prep_of">
            <governor idx="20">supporter</governor>
            <dependent idx="26">faction</dependent>
          </dep>
          <dep type="num">
            <governor idx="28">years</governor>
            <dependent idx="27">three</dependent>
          </dep>
          <dep type="tmod">
            <governor idx="4">killed</governor>
            <dependent idx="28">years</dependent>
          </dep>
          <dep type="advmod">
            <governor idx="28">years</governor>
            <dependent idx="29">later</dependent>
          </dep>
        </dependencies>
        <dependencies type="collapsed-ccprocessed-dependencies">
          <dep type="root">
            <governor idx="0">ROOT</governor>
            <dependent idx="4">killed</dependent>
          </dep>
          <dep type="cc">
            <governor idx="4">killed</governor>
            <dependent idx="1">But</dependent>
          </dep>
          <dep type="nsubjpass">
            <governor idx="4">killed</governor>
            <dependent idx="2">both</dependent>
          </dep>
          <dep type="auxpass">
            <governor idx="4">killed</governor>
            <dependent idx="3">were</dependent>
          </dep>
          <dep type="nn">
            <governor idx="7">Jihad</governor>
            <dependent idx="6">Abu</dependent>
          </dep>
          <dep type="dep">
            <governor idx="4">killed</governor>
            <dependent idx="7">Jihad</dependent>
          </dep>
          <dep type="det">
            <governor idx="12">squad</governor>
            <dependent idx="9">an</dependent>
          </dep>
          <dep type="amod">
            <governor idx="12">squad</governor>
            <dependent idx="10">Israeli</dependent>
          </dep>
          <dep type="amod">
            <governor idx="12">squad</governor>
            <dependent idx="11">hit</dependent>
          </dep>
          <dep type="prep_by">
            <governor idx="7">Jihad</governor>
            <dependent idx="12">squad</dependent>
          </dep>
          <dep type="prep_in">
            <governor idx="12">squad</governor>
            <dependent idx="14">1988</dependent>
          </dep>
          <dep type="nn">
            <governor idx="17">Iyad</governor>
            <dependent idx="16">Abu</dependent>
          </dep>
          <dep type="appos">
            <governor idx="14">1988</governor>
            <dependent idx="17">Iyad</dependent>
          </dep>
          <dep type="det">
            <governor idx="20">supporter</governor>
            <dependent idx="19">a</dependent>
          </dep>
          <dep type="agent">
            <governor idx="4">killed</governor>
            <dependent idx="20">supporter</dependent>
          </dep>
          <dep type="det">
            <governor idx="26">faction</governor>
            <dependent idx="22">the</dependent>
          </dep>
          <dep type="amod">
            <governor idx="26">faction</governor>
            <dependent idx="23">breakaway</dependent>
          </dep>
          <dep type="nn">
            <governor idx="26">faction</governor>
            <dependent idx="24">Abu</dependent>
          </dep>
          <dep type="nn">
            <governor idx="26">faction</governor>
            <dependent idx="25">Nidal</dependent>
          </dep>
          <dep type="prep_of">
            <governor idx="20">supporter</governor>
            <dependent idx="26">faction</dependent>
          </dep>
          <dep type="num">
            <governor idx="28">years</governor>
            <dependent idx="27">three</dependent>
          </dep>
          <dep type="tmod">
            <governor idx="4">killed</governor>
            <dependent idx="28">years</dependent>
          </dep>
          <dep type="advmod">
            <governor idx="28">years</governor>
            <dependent idx="29">later</dependent>
          </dep>
        </dependencies>
      </sentence>
    </sentences>
  </document>
</root>
