<?xml version="1.0" encoding="UTF-8"?>
<?xml-stylesheet href="CoreNLP-to-HTML.xsl" type="text/xsl"?>
<root>
  <document>
    <sentences>
      <sentence id="1">
        <tokens>
          <token id="1">
            <word>In</word>
            <CharacterOffsetBegin>0</CharacterOffsetBegin>
            <CharacterOffsetEnd>2</CharacterOffsetEnd>
            <POS>IN</POS>
          </token>
          <token id="2">
            <word>1975</word>
            <CharacterOffsetBegin>3</CharacterOffsetBegin>
            <CharacterOffsetEnd>7</CharacterOffsetEnd>
            <POS>CD</POS>
          </token>
          <token id="3">
            <word>,</word>
            <CharacterOffsetBegin>8</CharacterOffsetBegin>
            <CharacterOffsetEnd>9</CharacterOffsetEnd>
            <POS>,</POS>
          </token>
          <token id="4">
            <word>A.H.</word>
            <CharacterOffsetBegin>10</CharacterOffsetBegin>
            <CharacterOffsetEnd>14</CharacterOffsetEnd>
            <POS>NNP</POS>
          </token>
          <token id="5">
            <word>Robbins</word>
            <CharacterOffsetBegin>15</CharacterOffsetBegin>
            <CharacterOffsetEnd>22</CharacterOffsetEnd>
            <POS>NNP</POS>
          </token>
          <token id="6">
            <word>,</word>
            <CharacterOffsetBegin>23</CharacterOffsetBegin>
            <CharacterOffsetEnd>24</CharacterOffsetEnd>
            <POS>,</POS>
          </token>
          <token id="7">
            <word>a</word>
            <CharacterOffsetBegin>25</CharacterOffsetBegin>
            <CharacterOffsetEnd>26</CharacterOffsetEnd>
            <POS>DT</POS>
          </token>
          <token id="8">
            <word>Richmond</word>
            <CharacterOffsetBegin>27</CharacterOffsetBegin>
            <CharacterOffsetEnd>35</CharacterOffsetEnd>
            <POS>NNP</POS>
          </token>
          <token id="9">
            <word>,</word>
            <CharacterOffsetBegin>36</CharacterOffsetBegin>
            <CharacterOffsetEnd>37</CharacterOffsetEnd>
            <POS>,</POS>
          </token>
          <token id="10">
            <word>Va.</word>
            <CharacterOffsetBegin>38</CharacterOffsetBegin>
            <CharacterOffsetEnd>41</CharacterOffsetEnd>
            <POS>NNP</POS>
          </token>
          <token id="11">
            <word>,</word>
            <CharacterOffsetBegin>42</CharacterOffsetBegin>
            <CharacterOffsetEnd>43</CharacterOffsetEnd>
            <POS>,</POS>
          </token>
          <token id="12">
            <word>pharmaceutical</word>
            <CharacterOffsetBegin>44</CharacterOffsetBegin>
            <CharacterOffsetEnd>58</CharacterOffsetEnd>
            <POS>JJ</POS>
          </token>
          <token id="13">
            <word>company</word>
            <CharacterOffsetBegin>59</CharacterOffsetBegin>
            <CharacterOffsetEnd>66</CharacterOffsetEnd>
            <POS>NN</POS>
          </token>
          <token id="14">
            <word>that</word>
            <CharacterOffsetBegin>67</CharacterOffsetBegin>
            <CharacterOffsetEnd>71</CharacterOffsetEnd>
            <POS>WDT</POS>
          </token>
          <token id="15">
            <word>purchased</word>
            <CharacterOffsetBegin>72</CharacterOffsetBegin>
            <CharacterOffsetEnd>81</CharacterOffsetEnd>
            <POS>VBD</POS>
          </token>
          <token id="16">
            <word>manufacturing</word>
            <CharacterOffsetBegin>82</CharacterOffsetBegin>
            <CharacterOffsetEnd>95</CharacterOffsetEnd>
            <POS>NN</POS>
          </token>
          <token id="17">
            <word>rights</word>
            <CharacterOffsetBegin>96</CharacterOffsetBegin>
            <CharacterOffsetEnd>102</CharacterOffsetEnd>
            <POS>NNS</POS>
          </token>
          <token id="18">
            <word>for</word>
            <CharacterOffsetBegin>103</CharacterOffsetBegin>
            <CharacterOffsetEnd>106</CharacterOffsetEnd>
            <POS>IN</POS>
          </token>
          <token id="19">
            <word>the</word>
            <CharacterOffsetBegin>107</CharacterOffsetBegin>
            <CharacterOffsetEnd>110</CharacterOffsetEnd>
            <POS>DT</POS>
          </token>
          <token id="20">
            <word>Dalkon</word>
            <CharacterOffsetBegin>111</CharacterOffsetBegin>
            <CharacterOffsetEnd>117</CharacterOffsetEnd>
            <POS>NNP</POS>
          </token>
          <token id="21">
            <word>Shield</word>
            <CharacterOffsetBegin>118</CharacterOffsetBegin>
            <CharacterOffsetEnd>124</CharacterOffsetEnd>
            <POS>NNP</POS>
          </token>
          <token id="22">
            <word>from</word>
            <CharacterOffsetBegin>125</CharacterOffsetBegin>
            <CharacterOffsetEnd>129</CharacterOffsetEnd>
            <POS>IN</POS>
          </token>
          <token id="23">
            <word>Davis</word>
            <CharacterOffsetBegin>130</CharacterOffsetBegin>
            <CharacterOffsetEnd>135</CharacterOffsetEnd>
            <POS>NNP</POS>
          </token>
          <token id="24">
            <word>for</word>
            <CharacterOffsetBegin>136</CharacterOffsetBegin>
            <CharacterOffsetEnd>139</CharacterOffsetEnd>
            <POS>IN</POS>
          </token>
          <token id="25">
            <word>$</word>
            <CharacterOffsetBegin>140</CharacterOffsetBegin>
            <CharacterOffsetEnd>141</CharacterOffsetEnd>
            <POS>$</POS>
          </token>
          <token id="26">
            <word>750,000</word>
            <CharacterOffsetBegin>142</CharacterOffsetBegin>
            <CharacterOffsetEnd>149</CharacterOffsetEnd>
            <POS>CD</POS>
          </token>
          <token id="27">
            <word>,</word>
            <CharacterOffsetBegin>150</CharacterOffsetBegin>
            <CharacterOffsetEnd>151</CharacterOffsetEnd>
            <POS>,</POS>
          </token>
          <token id="28">
            <word>put</word>
            <CharacterOffsetBegin>152</CharacterOffsetBegin>
            <CharacterOffsetEnd>155</CharacterOffsetEnd>
            <POS>VBD</POS>
          </token>
          <token id="29">
            <word>2.2</word>
            <CharacterOffsetBegin>156</CharacterOffsetBegin>
            <CharacterOffsetEnd>159</CharacterOffsetEnd>
            <POS>CD</POS>
          </token>
          <token id="30">
            <word>million</word>
            <CharacterOffsetBegin>160</CharacterOffsetBegin>
            <CharacterOffsetEnd>167</CharacterOffsetEnd>
            <POS>CD</POS>
          </token>
          <token id="31">
            <word>of</word>
            <CharacterOffsetBegin>168</CharacterOffsetBegin>
            <CharacterOffsetEnd>170</CharacterOffsetEnd>
            <POS>IN</POS>
          </token>
          <token id="32">
            <word>the</word>
            <CharacterOffsetBegin>171</CharacterOffsetBegin>
            <CharacterOffsetEnd>174</CharacterOffsetEnd>
            <POS>DT</POS>
          </token>
          <token id="33">
            <word>intrauterine</word>
            <CharacterOffsetBegin>175</CharacterOffsetBegin>
            <CharacterOffsetEnd>187</CharacterOffsetEnd>
            <POS>JJ</POS>
          </token>
          <token id="34">
            <word>devices</word>
            <CharacterOffsetBegin>188</CharacterOffsetBegin>
            <CharacterOffsetEnd>195</CharacterOffsetEnd>
            <POS>NNS</POS>
          </token>
          <token id="35">
            <word>on</word>
            <CharacterOffsetBegin>196</CharacterOffsetBegin>
            <CharacterOffsetEnd>198</CharacterOffsetEnd>
            <POS>IN</POS>
          </token>
          <token id="36">
            <word>the</word>
            <CharacterOffsetBegin>199</CharacterOffsetBegin>
            <CharacterOffsetEnd>202</CharacterOffsetEnd>
            <POS>DT</POS>
          </token>
          <token id="37">
            <word>market</word>
            <CharacterOffsetBegin>203</CharacterOffsetBegin>
            <CharacterOffsetEnd>209</CharacterOffsetEnd>
            <POS>NN</POS>
          </token>
          <token id="38">
            <word>before</word>
            <CharacterOffsetBegin>210</CharacterOffsetBegin>
            <CharacterOffsetEnd>216</CharacterOffsetEnd>
            <POS>IN</POS>
          </token>
          <token id="39">
            <word>discontinuing</word>
            <CharacterOffsetBegin>217</CharacterOffsetBegin>
            <CharacterOffsetEnd>230</CharacterOffsetEnd>
            <POS>VBG</POS>
          </token>
          <token id="40">
            <word>production</word>
            <CharacterOffsetBegin>231</CharacterOffsetBegin>
            <CharacterOffsetEnd>241</CharacterOffsetEnd>
            <POS>NN</POS>
          </token>
          <token id="41">
            <word>in</word>
            <CharacterOffsetBegin>242</CharacterOffsetBegin>
            <CharacterOffsetEnd>244</CharacterOffsetEnd>
            <POS>IN</POS>
          </token>
          <token id="42">
            <word>1975</word>
            <CharacterOffsetBegin>245</CharacterOffsetBegin>
            <CharacterOffsetEnd>249</CharacterOffsetEnd>
            <POS>CD</POS>
          </token>
          <token id="43">
            <word>.</word>
            <CharacterOffsetBegin>250</CharacterOffsetBegin>
            <CharacterOffsetEnd>251</CharacterOffsetEnd>
            <POS>.</POS>
          </token>
        </tokens>
        <parse>(ROOT (S (PP (IN In) (NP (CD 1975))) (, ,) (NP (NP (NNP A.H.) (NNP Robbins)) (, ,) (NP (NP (DT a) (NAC (NNP Richmond) (, ,) (NNP Va.) (, ,)) (JJ pharmaceutical) (NN company)) (SBAR (WHNP (WDT that)) (S (VP (VBD purchased) (NP (NN manufacturing) (NNS rights)) (PP (IN for) (NP (DT the) (NNP Dalkon) (NNP Shield))) (PP (IN from) (NP (NP (NNP Davis)) (PP (IN for) (NP ($ $) (CD 750,000))))))))) (, ,)) (VP (VBD put) (NP (NP (QP (CD 2.2) (CD million))) (PP (IN of) (NP (NP (DT the) (JJ intrauterine) (NNS devices)) (PP (IN on) (NP (DT the) (NN market)))))) (PP (IN before) (S (VP (VBG discontinuing) (NP (NN production)) (PP (IN in) (NP (CD 1975))))))) (. .))) </parse>
        <dependencies type="basic-dependencies">
          <dep type="root">
            <governor idx="0">ROOT</governor>
            <dependent idx="28">put</dependent>
          </dep>
          <dep type="prep">
            <governor idx="28">put</governor>
            <dependent idx="1">In</dependent>
          </dep>
          <dep type="pobj">
            <governor idx="1">In</governor>
            <dependent idx="2">1975</dependent>
          </dep>
          <dep type="nn">
            <governor idx="5">Robbins</governor>
            <dependent idx="4">A.H.</dependent>
          </dep>
          <dep type="nsubj">
            <governor idx="28">put</governor>
            <dependent idx="5">Robbins</dependent>
          </dep>
          <dep type="det">
            <governor idx="13">company</governor>
            <dependent idx="7">a</dependent>
          </dep>
          <dep type="dep">
            <governor idx="13">company</governor>
            <dependent idx="8">Richmond</dependent>
          </dep>
          <dep type="dep">
            <governor idx="8">Richmond</governor>
            <dependent idx="10">Va.</dependent>
          </dep>
          <dep type="amod">
            <governor idx="13">company</governor>
            <dependent idx="12">pharmaceutical</dependent>
          </dep>
          <dep type="appos">
            <governor idx="5">Robbins</governor>
            <dependent idx="13">company</dependent>
          </dep>
          <dep type="nsubj">
            <governor idx="15">purchased</governor>
            <dependent idx="14">that</dependent>
          </dep>
          <dep type="rcmod">
            <governor idx="13">company</governor>
            <dependent idx="15">purchased</dependent>
          </dep>
          <dep type="nn">
            <governor idx="17">rights</governor>
            <dependent idx="16">manufacturing</dependent>
          </dep>
          <dep type="dobj">
            <governor idx="15">purchased</governor>
            <dependent idx="17">rights</dependent>
          </dep>
          <dep type="prep">
            <governor idx="15">purchased</governor>
            <dependent idx="18">for</dependent>
          </dep>
          <dep type="det">
            <governor idx="21">Shield</governor>
            <dependent idx="19">the</dependent>
          </dep>
          <dep type="nn">
            <governor idx="21">Shield</governor>
            <dependent idx="20">Dalkon</dependent>
          </dep>
          <dep type="pobj">
            <governor idx="18">for</governor>
            <dependent idx="21">Shield</dependent>
          </dep>
          <dep type="prep">
            <governor idx="15">purchased</governor>
            <dependent idx="22">from</dependent>
          </dep>
          <dep type="pobj">
            <governor idx="22">from</governor>
            <dependent idx="23">Davis</dependent>
          </dep>
          <dep type="prep">
            <governor idx="23">Davis</governor>
            <dependent idx="24">for</dependent>
          </dep>
          <dep type="pobj">
            <governor idx="24">for</governor>
            <dependent idx="25">$</dependent>
          </dep>
          <dep type="num">
            <governor idx="25">$</governor>
            <dependent idx="26">750,000</dependent>
          </dep>
          <dep type="number">
            <governor idx="30">million</governor>
            <dependent idx="29">2.2</dependent>
          </dep>
          <dep type="dobj">
            <governor idx="28">put</governor>
            <dependent idx="30">million</dependent>
          </dep>
          <dep type="prep">
            <governor idx="30">million</governor>
            <dependent idx="31">of</dependent>
          </dep>
          <dep type="det">
            <governor idx="34">devices</governor>
            <dependent idx="32">the</dependent>
          </dep>
          <dep type="amod">
            <governor idx="34">devices</governor>
            <dependent idx="33">intrauterine</dependent>
          </dep>
          <dep type="pobj">
            <governor idx="31">of</governor>
            <dependent idx="34">devices</dependent>
          </dep>
          <dep type="prep">
            <governor idx="34">devices</governor>
            <dependent idx="35">on</dependent>
          </dep>
          <dep type="det">
            <governor idx="37">market</governor>
            <dependent idx="36">the</dependent>
          </dep>
          <dep type="pobj">
            <governor idx="35">on</governor>
            <dependent idx="37">market</dependent>
          </dep>
          <dep type="prep">
            <governor idx="28">put</governor>
            <dependent idx="38">before</dependent>
          </dep>
          <dep type="pcomp">
            <governor idx="38">before</governor>
            <dependent idx="39">discontinuing</dependent>
          </dep>
          <dep type="dobj">
            <governor idx="39">discontinuing</governor>
            <dependent idx="40">production</dependent>
          </dep>
          <dep type="prep">
            <governor idx="39">discontinuing</governor>
            <dependent idx="41">in</dependent>
          </dep>
          <dep type="pobj">
            <governor idx="41">in</governor>
            <dependent idx="42">1975</dependent>
          </dep>
        </dependencies>
        <dependencies type="collapsed-dependencies">
          <dep type="root">
            <governor idx="0">ROOT</governor>
            <dependent idx="28">put</dependent>
          </dep>
          <dep type="prep_in">
            <governor idx="28">put</governor>
            <dependent idx="2">1975</dependent>
          </dep>
          <dep type="nn">
            <governor idx="5">Robbins</governor>
            <dependent idx="4">A.H.</dependent>
          </dep>
          <dep type="nsubj">
            <governor idx="28">put</governor>
            <dependent idx="5">Robbins</dependent>
          </dep>
          <dep type="det">
            <governor idx="13">company</governor>
            <dependent idx="7">a</dependent>
          </dep>
          <dep type="dep">
            <governor idx="13">company</governor>
            <dependent idx="8">Richmond</dependent>
          </dep>
          <dep type="dep">
            <governor idx="8">Richmond</governor>
            <dependent idx="10">Va.</dependent>
          </dep>
          <dep type="amod">
            <governor idx="13">company</governor>
            <dependent idx="12">pharmaceutical</dependent>
          </dep>
          <dep type="appos">
            <governor idx="5">Robbins</governor>
            <dependent idx="13">company</dependent>
          </dep>
          <dep type="nsubj">
            <governor idx="15">purchased</governor>
            <dependent idx="14">that</dependent>
          </dep>
          <dep type="rcmod">
            <governor idx="13">company</governor>
            <dependent idx="15">purchased</dependent>
          </dep>
          <dep type="nn">
            <governor idx="17">rights</governor>
            <dependent idx="16">manufacturing</dependent>
          </dep>
          <dep type="dobj">
            <governor idx="15">purchased</governor>
            <dependent idx="17">rights</dependent>
          </dep>
          <dep type="det">
            <governor idx="21">Shield</governor>
            <dependent idx="19">the</dependent>
          </dep>
          <dep type="nn">
            <governor idx="21">Shield</governor>
            <dependent idx="20">Dalkon</dependent>
          </dep>
          <dep type="prep_for">
            <governor idx="15">purchased</governor>
            <dependent idx="21">Shield</dependent>
          </dep>
          <dep type="prep_from">
            <governor idx="15">purchased</governor>
            <dependent idx="23">Davis</dependent>
          </dep>
          <dep type="prep_for">
            <governor idx="23">Davis</governor>
            <dependent idx="25">$</dependent>
          </dep>
          <dep type="num">
            <governor idx="25">$</governor>
            <dependent idx="26">750,000</dependent>
          </dep>
          <dep type="number">
            <governor idx="30">million</governor>
            <dependent idx="29">2.2</dependent>
          </dep>
          <dep type="dobj">
            <governor idx="28">put</governor>
            <dependent idx="30">million</dependent>
          </dep>
          <dep type="det">
            <governor idx="34">devices</governor>
            <dependent idx="32">the</dependent>
          </dep>
          <dep type="amod">
            <governor idx="34">devices</governor>
            <dependent idx="33">intrauterine</dependent>
          </dep>
          <dep type="prep_of">
            <governor idx="30">million</governor>
            <dependent idx="34">devices</dependent>
          </dep>
          <dep type="det">
            <governor idx="37">market</governor>
            <dependent idx="36">the</dependent>
          </dep>
          <dep type="prep_on">
            <governor idx="34">devices</governor>
            <dependent idx="37">market</dependent>
          </dep>
          <dep type="prepc_before">
            <governor idx="28">put</governor>
            <dependent idx="39">discontinuing</dependent>
          </dep>
          <dep type="dobj">
            <governor idx="39">discontinuing</governor>
            <dependent idx="40">production</dependent>
          </dep>
          <dep type="prep_in">
            <governor idx="39">discontinuing</governor>
            <dependent idx="42">1975</dependent>
          </dep>
        </dependencies>
        <dependencies type="collapsed-ccprocessed-dependencies">
          <dep type="root">
            <governor idx="0">ROOT</governor>
            <dependent idx="28">put</dependent>
          </dep>
          <dep type="prep_in">
            <governor idx="28">put</governor>
            <dependent idx="2">1975</dependent>
          </dep>
          <dep type="nn">
            <governor idx="5">Robbins</governor>
            <dependent idx="4">A.H.</dependent>
          </dep>
          <dep type="nsubj">
            <governor idx="28">put</governor>
            <dependent idx="5">Robbins</dependent>
          </dep>
          <dep type="det">
            <governor idx="13">company</governor>
            <dependent idx="7">a</dependent>
          </dep>
          <dep type="dep">
            <governor idx="13">company</governor>
            <dependent idx="8">Richmond</dependent>
          </dep>
          <dep type="dep">
            <governor idx="8">Richmond</governor>
            <dependent idx="10">Va.</dependent>
          </dep>
          <dep type="amod">
            <governor idx="13">company</governor>
            <dependent idx="12">pharmaceutical</dependent>
          </dep>
          <dep type="appos">
            <governor idx="5">Robbins</governor>
            <dependent idx="13">company</dependent>
          </dep>
          <dep type="nsubj">
            <governor idx="15">purchased</governor>
            <dependent idx="14">that</dependent>
          </dep>
          <dep type="rcmod">
            <governor idx="13">company</governor>
            <dependent idx="15">purchased</dependent>
          </dep>
          <dep type="nn">
            <governor idx="17">rights</governor>
            <dependent idx="16">manufacturing</dependent>
          </dep>
          <dep type="dobj">
            <governor idx="15">purchased</governor>
            <dependent idx="17">rights</dependent>
          </dep>
          <dep type="det">
            <governor idx="21">Shield</governor>
            <dependent idx="19">the</dependent>
          </dep>
          <dep type="nn">
            <governor idx="21">Shield</governor>
            <dependent idx="20">Dalkon</dependent>
          </dep>
          <dep type="prep_for">
            <governor idx="15">purchased</governor>
            <dependent idx="21">Shield</dependent>
          </dep>
          <dep type="prep_from">
            <governor idx="15">purchased</governor>
            <dependent idx="23">Davis</dependent>
          </dep>
          <dep type="prep_for">
            <governor idx="23">Davis</governor>
            <dependent idx="25">$</dependent>
          </dep>
          <dep type="num">
            <governor idx="25">$</governor>
            <dependent idx="26">750,000</dependent>
          </dep>
          <dep type="number">
            <governor idx="30">million</governor>
            <dependent idx="29">2.2</dependent>
          </dep>
          <dep type="dobj">
            <governor idx="28">put</governor>
            <dependent idx="30">million</dependent>
          </dep>
          <dep type="det">
            <governor idx="34">devices</governor>
            <dependent idx="32">the</dependent>
          </dep>
          <dep type="amod">
            <governor idx="34">devices</governor>
            <dependent idx="33">intrauterine</dependent>
          </dep>
          <dep type="prep_of">
            <governor idx="30">million</governor>
            <dependent idx="34">devices</dependent>
          </dep>
          <dep type="det">
            <governor idx="37">market</governor>
            <dependent idx="36">the</dependent>
          </dep>
          <dep type="prep_on">
            <governor idx="34">devices</governor>
            <dependent idx="37">market</dependent>
          </dep>
          <dep type="prepc_before">
            <governor idx="28">put</governor>
            <dependent idx="39">discontinuing</dependent>
          </dep>
          <dep type="dobj">
            <governor idx="39">discontinuing</governor>
            <dependent idx="40">production</dependent>
          </dep>
          <dep type="prep_in">
            <governor idx="39">discontinuing</governor>
            <dependent idx="42">1975</dependent>
          </dep>
        </dependencies>
      </sentence>
    </sentences>
  </document>
</root>
